tvalidation.py
tvalidation-0.0.2.dist-info/METADATA
tvalidation-0.0.2.dist-info/WHEEL
tvalidation-0.0.2.dist-info/top_level.txt
tvalidation-0.0.2.dist-info/RECORD
